midas_client/__init__.py
midas_client/client.py
midas_client/historical.py
midas_client/instrument.py
midas_client/trading.py
midas_client/utils.py
midas_client-1.0.23.dist-info/METADATA
midas_client-1.0.23.dist-info/WHEEL
midas_client-1.0.23.dist-info/top_level.txt
midas_client-1.0.23.dist-info/RECORD
